.gitignore
.gitlab-ci.yml
AUTHORS
CHANGELOG.md
CMakeLists.txt
LICENSE
README.md
config.h.cmake
dune-spgrid.pc.in
dune.module
pyproject.toml
setup.py
cmake/modules/CMakeLists.txt
cmake/modules/DuneSpgridMacros.cmake
doc/.gitignore
doc/CMakeLists.txt
doc/doxygen/CMakeLists.txt
doc/doxygen/Doxylocal
doc/doxygen/main.page
doc/doxygen/structure.page
dune/.gitignore
dune/CMakeLists.txt
dune/common/.gitignore
dune/common/CMakeLists.txt
dune/common/iostream.hh
dune/grid/.gitignore
dune/grid/CMakeLists.txt
dune/grid/spgrid.hh
dune/grid/extensions/.gitignore
dune/grid/extensions/CMakeLists.txt
dune/grid/extensions/superentityiterator.hh
dune/grid/spgrid/.gitignore
dune/grid/spgrid/CMakeLists.txt
dune/grid/spgrid/backuprestore.hh
dune/grid/spgrid/boundarysegmentiterator.hh
dune/grid/spgrid/cachedpartitionlist.hh
dune/grid/spgrid/capabilities.hh
dune/grid/spgrid/communication.hh
dune/grid/spgrid/cube.hh
dune/grid/spgrid/declaration.hh
dune/grid/spgrid/decomposition.hh
dune/grid/spgrid/dgfparser.hh
dune/grid/spgrid/direction.hh
dune/grid/spgrid/domain.hh
dune/grid/spgrid/entity.hh
dune/grid/spgrid/entityinfo.hh
dune/grid/spgrid/entityseed.hh
dune/grid/spgrid/fileio.hh
dune/grid/spgrid/geometricgridlevel.hh
dune/grid/spgrid/geometry.hh
dune/grid/spgrid/geometrycache.hh
dune/grid/spgrid/grid.hh
dune/grid/spgrid/gridlevel.hh
dune/grid/spgrid/gridview.hh
dune/grid/spgrid/hierarchiciterator.hh
dune/grid/spgrid/hierarchicsearch.hh
dune/grid/spgrid/hindexset.hh
dune/grid/spgrid/idset.hh
dune/grid/spgrid/indexset.hh
dune/grid/spgrid/intersection.hh
dune/grid/spgrid/intersectioniterator.hh
dune/grid/spgrid/iterator.hh
dune/grid/spgrid/linkage.hh
dune/grid/spgrid/mesh.hh
dune/grid/spgrid/messagebuffer.hh
dune/grid/spgrid/misc.hh
dune/grid/spgrid/multiindex.hh
dune/grid/spgrid/normal.hh
dune/grid/spgrid/partition.hh
dune/grid/spgrid/partitionlist.hh
dune/grid/spgrid/partitionpool.hh
dune/grid/spgrid/persistentcontainer.hh
dune/grid/spgrid/referencecube.hh
dune/grid/spgrid/refinement.hh
python/dune_spgrid.egg-info/PKG-INFO
python/dune_spgrid.egg-info/SOURCES.txt
python/dune_spgrid.egg-info/dependency_links.txt
python/dune_spgrid.egg-info/requires.txt
python/dune_spgrid.egg-info/top_level.txt