Metadata-Version: 2.1
Name: dune-spgrid
Version: 2.11.dev20250709
Summary: module providing a structured grid
Home-page: https://gitlab.dune-project.org/extensions/dune-spgrid
Author: Martin Nolte
Author-email: nolte.mrtn@gmail.com
Classifier: Programming Language :: C++
Classifier: Programming Language :: Python :: 3
Classifier: License :: OSI Approved :: GNU General Public License (GPL)
Requires-Python: >=3.4
License-File: LICENSE
License-File: AUTHORS
